setup.py
p3/__init__.py
p3/p3.py
p3.egg-info/PKG-INFO
p3.egg-info/SOURCES.txt
p3.egg-info/dependency_links.txt
p3.egg-info/requires.txt
p3.egg-info/top_level.txt