Metadata-Version: 1.1
Name: p3
Version: 0.1.2
Summary: a minimal d3 for python
Home-page: UNKNOWN
Author: Sam Williams
Author-email: samueltwilliams@gmail.com
License: MIT
Platform: UNKNOWN
Classifier: Programming Language :: Python :: 2
